otp_generator/__init__.py
otp_generator/otp.py
simple_otp_generator-0.1.2.dist-info/LICENSE
simple_otp_generator-0.1.2.dist-info/METADATA
simple_otp_generator-0.1.2.dist-info/WHEEL
simple_otp_generator-0.1.2.dist-info/top_level.txt
simple_otp_generator-0.1.2.dist-info/RECORD
