Metadata-Version: 2.1
Name: simple-otp-generator
Version: 0.1.2
Summary: A simple OTP generator
Home-page: https://github.com/yourusername/otp-generator
Author: Gaurav Borade
Author-email: gauravwinjitwork@gmail.com
Classifier: Programming Language :: Python :: 3
Classifier: License :: OSI Approved :: MIT License
Classifier: Operating System :: OS Independent
Requires-Python: >=3.6
License-File: LICENSE
